dcmanon-0.3.1.dist-info/METADATA
dcmanon-0.3.1.dist-info/WHEEL
dcmanon/__init__.py
dcmanon/dcmanon.cp39-win_amd64.pyd
dcmanon-0.3.1.dist-info/RECORD
