Metadata-Version: 2.4
Name: dcmanon
Version: 0.3.1
Classifier: Development Status :: 3 - Alpha
Classifier: Intended Audience :: Developers
Classifier: Intended Audience :: Healthcare Industry
Classifier: Operating System :: MacOS
Classifier: Operating System :: Microsoft
Classifier: Operating System :: POSIX :: Linux
Classifier: Programming Language :: Rust
Classifier: Programming Language :: Python :: Implementation :: CPython
Classifier: Programming Language :: Python :: Implementation :: PyPy
Classifier: Topic :: Software Development :: Libraries :: Python Modules
Summary: Lightning-fast DICOM anonymization for Python, written in Rust.
Keywords: dicom,anonymization,python,rust
Author-email: Sander Smits <sander@carecoders.io>
Maintainer-email: Sander Smits <sander@carecoders.io>
License: MIT OR Apache-2.0
Requires-Python: >=3.8
Project-URL: Homepage, https://github.com/carecoders/dicom-anonymization
Project-URL: Repository, https://github.com/carecoders/dicom-anonymization.git
Project-URL: Issues, https://github.com/carecoders/dicom-anonymization/issues
Project-URL: Changelog, https://github.com/carecoders/dicom-anonymization/blob/main/CHANGELOG.md
